setup.py
droopy/__init__.py
droopy/factory.py
droopy/filters.py
droopy/full.py
droopy/readability.py
droopy/static.py
droopy.egg-info/PKG-INFO
droopy.egg-info/SOURCES.txt
droopy.egg-info/dependency_links.txt
droopy.egg-info/top_level.txt
droopy/lang/__init__.py
droopy/lang/en_syllables_cmudict.py
droopy/lang/english.py
droopy/lang/polish.py
tests/__init__.py