Metadata-Version: 1.0
Name: droopy
Version: 0.0.3
Summary: Little library for text analysis
Home-page: https://github.com/ifrost/droopy
Author: Piotr Jamroz
Author-email: pm.jamroz@gmail.com
License: MIT
Keywords: text analysis readability
Platform: UNKNOWN
Classifier: Development Status :: 4 - Beta
Classifier: Topic :: Utilities
